django_ormcache-1.4.dist-info/licenses/LICENSE
ormcache/__init__.py
ormcache/decorators.py
ormcache/managers.py
ormcache/models.py
ormcache/queryset.py
ormcache/signals.py
ormcache/utils.py
django_ormcache-1.4.dist-info/METADATA
django_ormcache-1.4.dist-info/WHEEL
django_ormcache-1.4.dist-info/top_level.txt
django_ormcache-1.4.dist-info/RECORD
